py_velocity_rest_client/Velocity.py
py_velocity_rest_client/__init__.py
py_velocity_rest_client-0.1.dist-info/LICENSE
py_velocity_rest_client-0.1.dist-info/METADATA
py_velocity_rest_client-0.1.dist-info/WHEEL
py_velocity_rest_client-0.1.dist-info/top_level.txt
py_velocity_rest_client-0.1.dist-info/zip-safe
py_velocity_rest_client-0.1.dist-info/RECORD
